target_weaviate/__init__.py
target_weaviate/client.py
target_weaviate/sinks.py
target_weaviate/target.py
target_weaviate-0.1.0.dist-info/METADATA
target_weaviate-0.1.0.dist-info/WHEEL
target_weaviate-0.1.0.dist-info/entry_points.txt
target_weaviate-0.1.0.dist-info/licenses/LICENSE
target_weaviate-0.1.0.dist-info/RECORD
