Metadata-Version: 2.4
Name: target-weaviate
Version: 0.1.0
Summary: `target-weaviate` is a Singer target for Weaviate, built with the Meltano Singer SDK.
License: Apache-2.0
License-File: LICENSE
Keywords: ELT,Weaviate,Singer,Meltano
Author: Steven Searcy
Author-email: steven@foodhealth.co
Requires-Python: >=3.9,<3.13
Classifier: License :: OSI Approved :: Apache Software License
Classifier: Programming Language :: Python :: 3
Classifier: Programming Language :: Python :: 3.9
Classifier: Programming Language :: Python :: 3.10
Classifier: Programming Language :: Python :: 3.11
Classifier: Programming Language :: Python :: 3.12
Requires-Dist: requests (>=2.31.0,<3.0.0)
Requires-Dist: singer-sdk (>=0.48.1,<0.49.0)
Requires-Dist: weaviate-client (>=4.9.0,<5.0.0)
